{
  "version": "2.8.0",
  "notes_en": [
    "MCP server now runs standalone — no GUI needed",
    "Rebuilt on official MCP C# SDK (ModelContextProtocol v1.2.0)",
    "Search safety: input validation, response size limits",
    "Available on Windows and macOS (Intel + Apple Silicon)"
  ],
  "notes_ko": [
    "MCP 서버 독립 실행 — GUI 없이 동작",
    "공식 MCP C# SDK (ModelContextProtocol v1.2.0) 기반 재구축",
    "검색 안전성: 입력 검증, 응답 크기 제한",
    "Windows 및 macOS (Intel + Apple Silicon) 지원"
  ],
  "notes_fr": [
    "Le serveur MCP fonctionne désormais de manière autonome",
    "Reconstruit sur le SDK MCP C# officiel (v1.2.0)",
    "Sécurité de recherche : validation des entrées, limites de taille",
    "Disponible sur Windows et macOS (Intel + Apple Silicon)"
  ],
  "notes_de": [
    "MCP-Server läuft jetzt eigenständig — keine GUI erforderlich",
    "Auf offiziellem MCP C# SDK (v1.2.0) neu aufgebaut",
    "Suchsicherheit: Eingabevalidierung, Antwortgrößenlimits",
    "Verfügbar für Windows und macOS (Intel + Apple Silicon)"
  ],
  "notes_zh": [
    "MCP 服务器现在可以独立运行 — 无需 GUI",
    "基于官方 MCP C# SDK (v1.2.0) 重建",
    "搜索安全性：输入验证、响应大小限制",
    "支持 Windows 和 macOS（Intel + Apple Silicon）"
  ]
}
